sfdutf7/__init__.py
sfdutf7/__main__.py
sfdutf7/xmlvalid.py
sfdutf7-0.1.0.dist-info/LICENSE.txt
sfdutf7-0.1.0.dist-info/METADATA
sfdutf7-0.1.0.dist-info/WHEEL
sfdutf7-0.1.0.dist-info/entry_points.txt
sfdutf7-0.1.0.dist-info/top_level.txt
sfdutf7-0.1.0.dist-info/RECORD
