Metadata-Version: 2.1
Name: sfdutf7
Version: 0.1.0
Summary: SFDUTF7 encoding parsing library
Home-page: https://github.com/ctrlcctrlv/sfdutf7.py
Author: Fredrick Brennan
Author-email: copypaste@kittens.ph
Classifier: Programming Language :: Python :: 3
Classifier: License :: OSI Approved :: Apache Software License
Classifier: Operating System :: OS Independent
Requires-Python: >=3.6
License-File: LICENSE.txt
